sachac_plover_retro_stroke/__init__.py
sachac_plover_retro_stroke-0.1.0.dist-info/LICENSE
sachac_plover_retro_stroke-0.1.0.dist-info/METADATA
sachac_plover_retro_stroke-0.1.0.dist-info/WHEEL
sachac_plover_retro_stroke-0.1.0.dist-info/entry_points.txt
sachac_plover_retro_stroke-0.1.0.dist-info/top_level.txt
sachac_plover_retro_stroke-0.1.0.dist-info/zip-safe
sachac_plover_retro_stroke-0.1.0.dist-info/RECORD
